CHANGES.rst
CONTRIBUTORS.rst
MANIFEST.in
README.rst
VERSION
VERSION_SUFFIX
pyproject.toml
setup.cfg
setup.py
docs/index.rst
docs/resources/contentPython.html
docs/sample/async.py
docs/sample/simple.py
docs/sample/stream.py
src/pdfreactor/__init__.py
src/pdfreactor/_args.py
src/pdfreactor/api.py
src/pdfreactor/defaults.py
src/pdfreactor/exceptions.py
src/pdfreactor_api.egg-info/PKG-INFO
src/pdfreactor_api.egg-info/SOURCES.txt
src/pdfreactor_api.egg-info/dependency_links.txt
src/pdfreactor_api.egg-info/namespace_packages.txt
src/pdfreactor_api.egg-info/not-zip-safe
src/pdfreactor_api.egg-info/requires.txt
src/pdfreactor_api.egg-info/top_level.txt