Metadata-Version: 2.1
Name: pdfreactor-api
Version: 1.8.1.post0
Summary: Python API for PDFreactor
Home-page: UNKNOWN
Author: Tobias Herp
Author-email: tobias.herp@visaplan.com
License: MIT License
Project-URL: Source, https://github.com/visaplan/pdfreactor-api
Project-URL: Documentation, https://pypi.org/project/pdfreactor-api
Project-URL: Tracker, https://github.com/visaplan/pdfreactor-api/issues
Platform: UNKNOWN
Classifier: Environment :: Web Environment
Classifier: Programming Language :: Python
Classifier: Programming Language :: Python :: 2.6
Classifier: Programming Language :: Python :: 2.7
Classifier: Programming Language :: Python :: 3.4
Classifier: Programming Language :: Python :: 3.5
Classifier: Programming Language :: Python :: 3.6
Classifier: Programming Language :: Python :: 3.7
Classifier: Intended Audience :: Developers
Classifier: Operating System :: OS Independent
Classifier: License :: OSI Approved :: MIT License
